.gitignore
.travis.yml
MANIFEST.in
Makefile
README.rst
bootstrap.py
bower.json
package.json
setup.py
travis.cfg
docs/HISTORY.txt
docs/INSTALL.txt
docs/LICENSE.GPL
docs/LICENSE.txt
src/collective/__init__.py
src/collective.geo.openlayers.egg-info/PKG-INFO
src/collective.geo.openlayers.egg-info/SOURCES.txt
src/collective.geo.openlayers.egg-info/dependency_links.txt
src/collective.geo.openlayers.egg-info/entry_points.txt
src/collective.geo.openlayers.egg-info/namespace_packages.txt
src/collective.geo.openlayers.egg-info/not-zip-safe
src/collective.geo.openlayers.egg-info/requires.txt
src/collective.geo.openlayers.egg-info/top_level.txt
src/collective/geo/__init__.py
src/collective/geo/openlayers/__init__.py
src/collective/geo/openlayers/configure.zcml
src/collective/geo/openlayers/profiles.zcml
src/collective/geo/openlayers/testing.py
src/collective/geo/openlayers/testing.zcml
src/collective/geo/openlayers/upgrades.py
src/collective/geo/openlayers/browser/__init__.py
src/collective/geo/openlayers/browser/configure.zcml
src/collective/geo/openlayers/browser/interfaces.py
src/collective/geo/openlayers/browser/static/geo-openlayers.css
src/collective/geo/openlayers/browser/static/proj4js-compressed.js
src/collective/geo/openlayers/browser/static/openlayers/OpenLayers.js
src/collective/geo/openlayers/browser/static/openlayers/Lang/ar.js
src/collective/geo/openlayers/browser/static/openlayers/Lang/be-tarask.js
src/collective/geo/openlayers/browser/static/openlayers/Lang/bg.js
src/collective/geo/openlayers/browser/static/openlayers/Lang/br.js
src/collective/geo/openlayers/browser/static/openlayers/Lang/ca.js
src/collective/geo/openlayers/browser/static/openlayers/Lang/cs-CZ.js
src/collective/geo/openlayers/browser/static/openlayers/Lang/da-DK.js
src/collective/geo/openlayers/browser/static/openlayers/Lang/de.js
src/collective/geo/openlayers/browser/static/openlayers/Lang/el.js
src/collective/geo/openlayers/browser/static/openlayers/Lang/en-CA.js
src/collective/geo/openlayers/browser/static/openlayers/Lang/en.js
src/collective/geo/openlayers/browser/static/openlayers/Lang/es.js
src/collective/geo/openlayers/browser/static/openlayers/Lang/fi.js
src/collective/geo/openlayers/browser/static/openlayers/Lang/fr.js
src/collective/geo/openlayers/browser/static/openlayers/Lang/fur.js
src/collective/geo/openlayers/browser/static/openlayers/Lang/gl.js
