Metadata-Version: 1.1
Name: collective.geo.openlayers
Version: 4.0
Summary: openlayers support for Plone
Home-page: https://github.com/collective/collective.geo.openlayers
Author: Giorgio Borelli
Author-email: giorgio@giorgioborelli.it
License: GPL
Keywords: Zope Plone GIS KML Google Maps Bing OpenLayers
Platform: UNKNOWN
Classifier: Framework :: Plone
Classifier: Topic :: Internet
Classifier: Topic :: Scientific/Engineering :: GIS
Classifier: Programming Language :: Python
